<?xml version="1.0" encoding="UTF-8"?>
<!--
This software is in the public domain under CC0 1.0 Universal plus a 
Grant of Patent License.

To the extent possible under law, the author(s) have dedicated all
copyright and related and neighboring rights to this software to the
public domain worldwide. This software is distributed without any
warranty.

You should have received a copy of the CC0 Public Domain Dedication
along with this software (see the LICENSE.md file). If not, see
<http://creativecommons.org/publicdomain/zero/1.0/>.
-->
<screen xmlns:xsi="http://www.w3.org/2001/XMLSchema-instance"
        xsi:noNamespaceSchemaLocation="http://moqui.org/xsd/xml-screen-2.1.xsd"
        default-menu-title="Time" default-menu-index="1">

    <parameter name="workEffortId" required="true"/>

    <transition name="editUser"><default-response url="//hmadmin/User/EditUser"/></transition>
    <transition name="addTaskTime"><service-call name="mantle.work.TaskServices.add#TaskTime"/>
        <default-response url="."/></transition>
    <transition name="deleteTimeEntry"><service-call name="delete#mantle.work.time.TimeEntry"/>
        <default-response url="."/></transition>

    <actions>
        <entity-find-one entity-name="mantle.work.effort.WorkEffort" value-field="workEffort"/>
        <entity-find entity-name="mantle.work.time.TimeEntry" list="timeEntryList">
            <econdition field-name="workEffortId"/>
            <order-by field-name="fromDate"/><order-by field-name="lastUpdatedStamp"/>
        </entity-find>
    </actions>
    <widgets>
        <form-single name="AddTaskTime" transition="addTaskTime">
            <field name="workEffortId"><default-field><hidden/></default-field></field>
            <field name="partyId"><default-field title="Worker">
                <drop-down no-current-selected-key="${ec.user.userAccount.partyId}" current="selected">
                    <entity-options key="${partyId}" text="${firstName} ${lastName} (${partyId})">
                        <entity-find entity-name="WorkEffortPartyAndPerson">
                            <date-filter/>
                            <econdition field-name="workEffortId"/>
                        </entity-find>
                    </entity-options>
                </drop-down>
            </default-field></field>
            <field name="rateTypeEnumId"><default-field title="Rate Type">
                <drop-down no-current-selected-key="RatpStandard"><entity-options key="${enumId}" text="${description}">
                    <entity-find entity-name="moqui.basic.Enumeration"><econdition field-name="enumTypeId" value="RateType"/></entity-find>
                </entity-options></drop-down>
            </default-field></field>
            <field name="comments"><default-field><text-area cols="60" rows="3"/></default-field></field>
            <field name="remainingWorkTime"><default-field title="Remaining Hours">
                <text-line size="5"/></default-field></field>
            <field name="curRemainingWorkTime" from="workEffort.remainingWorkTime"><default-field title="Current Rem Hours">
                <display/></default-field></field>

            <field name="pieceCount"><default-field><text-line size="6"/></default-field></field>
            <field name="breakHours"><default-field><text-line size="5" default-value="0"/></default-field></field>
            <field name="instructions"><default-field title="">
                <display text="Enter values for 2 of the 3 below, or just Hours and Thru will be set to now"/>
            </default-field></field>
            <field name="hours"><default-field><text-line size="5"/></default-field></field>
            <field name="fromDate"><default-field title="From"><date-time/></default-field></field>
            <field name="thruDate"><default-field title="Thru"><date-time/></default-field></field>

            <field name="submitButton"><default-field title="Add Time"><submit/></default-field></field>

            <field-layout>
                <field-row><field-ref name="partyId"/><field-ref name="rateTypeEnumId"/></field-row>
                <field-ref name="comments"/>
                <field-row><field-ref name="curRemainingWorkTime"/><field-ref name="breakHours"/></field-row>
                <field-row><field-ref name="remainingWorkTime"/><field-ref name="pieceCount"/></field-row>
                <field-ref name="instructions"/>
                <field-ref name="hours"/>
                <field-row><field-ref name="fromDate"/><field-ref name="thruDate"/></field-row>
                <field-ref name="submitButton"/>
            </field-layout>
        </form-single>

        <form-list name="TimeEntryList" list="timeEntryList" skip-form="true">
            <row-actions>
                <!-- don't show rates to general users: <entity-find-one entity-name="mantle.humanres.rate.RateAmount" value-field="rateAmount" cache="true"/> -->
            </row-actions>
            <!-- <field name="timeEntryId"><default-field title="ID"><display also-hidden="false"/></default-field></field> -->
            <field name="partyId"><default-field title="User">
                <link url="editUser" entity-name="mantle.party.PartyDetail" text="PartyNameTemplate" link-type="anchor"/>
            </default-field></field>
            <field name="comments"><default-field><display also-hidden="false"/></default-field></field>
            <field name="hours"><default-field><display format="0.00" also-hidden="false"/></default-field></field>
            <field name="breakHours"><default-field title="Break"><display format="0.00" also-hidden="false"/></default-field></field>
            <field name="timeRange"><default-field><display text="${ec.l10n.format(fromDate, '')} - ${ec.l10n.format(thruDate, '')}" also-hidden="false"/></default-field></field>
            <field name="rateTypeEnumId"><default-field title="Rate Type"><display-entity entity-name="moqui.basic.Enumeration" key-field-name="enumId"/></default-field></field>
            <!-- don't show rates to general users:
            <field name="amount">
                <conditional-field condition="rateAmount">
                    <display text="${hours*rateAmount.rateAmount}" currency-unit-field="rateAmount.rateCurrencyUomId"/>
                </conditional-field>
                <default-field><display text=""/></default-field>
            </field>
            <field name="invoice"><default-field><display text="${invoiceId?:''}:${invoiceItemSeqId?:''}" also-hidden="false"/></default-field></field>
            -->
            <field name="deleteButton"><default-field title="">
                <link url="deleteTimeEntry" text="Delete" confirmation="Are you sure?"/></default-field></field>
        </form-list>
    </widgets>
</screen>
